pyocd_mpsse/__init__.py
pyocd_mpsse/mpsse_probe.py
pyocd_mpsse-0.1.3.dist-info/LICENSE
pyocd_mpsse-0.1.3.dist-info/METADATA
pyocd_mpsse-0.1.3.dist-info/WHEEL
pyocd_mpsse-0.1.3.dist-info/entry_points.txt
pyocd_mpsse-0.1.3.dist-info/RECORD
