Metadata-Version: 2.3
Name: pyocd-mpsse
Version: 0.1.3
Summary: PyOCD debug probe plugin for the MPSSE mode of FTDI chips
License: Apache-2.0
Author: Andreas Fritiofson
Author-email: andreas@fritiofson.net
Requires-Python: >=3.7
Classifier: License :: OSI Approved :: Apache Software License
Classifier: Programming Language :: Python :: 3
Classifier: Programming Language :: Python :: 3.7
Classifier: Programming Language :: Python :: 3.8
Classifier: Programming Language :: Python :: 3.9
Classifier: Programming Language :: Python :: 3.10
Classifier: Programming Language :: Python :: 3.11
Classifier: Programming Language :: Python :: 3.12
Classifier: Programming Language :: Python :: 3.13
Requires-Dist: pyocd (>=0.36.0)
